spotcrates/__init__.py
spotcrates/cli.py
spotcrates/common.py
spotcrates/filters.py
spotcrates/playlists.py
spotcrates-0.8.1.dist-info/METADATA
spotcrates-0.8.1.dist-info/WHEEL
spotcrates-0.8.1.dist-info/entry_points.txt
spotcrates-0.8.1.dist-info/licenses/LICENSE
spotcrates-0.8.1.dist-info/RECORD
