Metadata-Version: 2.4
Name: spotcrates
Version: 0.8.1
Author-email: Chris Mayes <cmayes@cmay.es>
License-File: LICENSE
Requires-Python: >=3.10
Requires-Dist: appdirs>=1.4.4
Requires-Dist: cython>=3.0.4
Requires-Dist: durations-nlp>=1.0.1
Requires-Dist: jinja2>=3.1.2
Requires-Dist: pygtrie>=2.5.0
Requires-Dist: setuptools>=80.8.0
Requires-Dist: spotipy>=2.22.1
Requires-Dist: tomli-w>=1.0.0
Requires-Dist: tomli>=2.0.1
Requires-Dist: types-appdirs>=1.4.3.5
